Workbook

Sheet Summary
A1: Pricing Model Analysis & Implementation Workbook
A3: What this workbook gives you
A4: 1) Current pricing model extracted exactly from your original file.
A5: 2) Proposed base prices and add-on economics with editable assumptions.
A6: 3) Usage-driven tier calculator (monthly and annual total cost).
A7: 4) Upgrade passage mechanism (soft warning -> hard limit -> next-tier recommendation).
A8: 5) Architecture blueprint mapped to your existing Booking-Engine-CMS backend.
A11: Key finding from source file
A12: Only Starter has explicit base price in source: 6 USD/month or 70 USD/year. Freelance and Enterprise base prices are missing and must be finalized.
A14: Recommended usage flow in product
A15: - Collect usage events daily (instances, domains, messages, bookings, backlinks).
A16: - Aggregate per tenant + billing cycle.
... A18: - Write invoice line items and send upgrade suggestions when threshold rules are met.

Sheet Current_Model_Extract
A1: Current Model Extract (from /Users/dilandilaruksha/Downloads/Pricing model.xlsx)
A3: Source Row | B3: Description | C3: Free | D3: Starter | E3: Freelance | F3: Enterprise
A4: 1 | B4: Anually | C4: 0 | D4: 70 UDS
A5: 2 | B5: monthly | C5: 0 | D5: 6 USD
A6: 5 | B6: Description | C6: Free | D6: Starter | E6: Freelance | F6: Enterprise
A7: 6 | B7: Instance | C7: 1 | D7: 1 | E7: 10 | F7: 100
A8: 7 | B8: Custom domains | C8: 10 USD | D8: 1 | E8: 10 | F8: 100
A9: 8 | B9: Add-on Instance + Domain | C9: No | D9: 3 USD / pm 24 USD / pa | E9: 3 USD / pm 24 USD / pa | F9: 3 USD / pm 24 USD / pa
A10: 9 | B10: No of pages / per web | C10: 5 Pages | D10: 25 Pages | E10: 25 Pages | F10: Unlimited
A11: 10 | B11: Accessible Themes | C11: 10 | D11: 100 | E11: 100 | F11: 100
A12: 11 | B12: Premium Templates | C12: No | D12: Yes | E12: Yes | F12: Yes
A13: 12 | B13: Technical Support | C13: Limited | D13: Full | E13: Full | F13: Full
A14: 13 | B14: Claim Dynamic Ads | C14: No | D14: Yes | E14: Yes | F14: Yes
A15: 15 | B15: Bookings per day | C15: 10 | D15: Unlimited | E15: Unlimited | F15: Unlimited
A16: 16 | B16: Active Services to Display | C16: 5 | D16: Unlimited | E16: Unlimited | F16: Unlimited
A17: 17 | B17: Staff accounts creation | C17: No | D17: Yes | E17: Yes | F17: Yes
A18: 19 | B18: SEO Content Auto Generation | C18: No | D18: Yes | E18: Yes | F18: Yes
A19: 20 | B19: AEO Data feeding | C19: No | D19: Yes | E19: Yes | F19: Yes
A20: 22 | B20: Inbox Automation | C20: 50 messages / per day | D20: 200 messages / pd / pi | E20: 200 messages / pd / pi | F20: 200 messages / pd / pi
A21: 23 | B21: Additional messages | C21: 0.05 USD / pm | D21: 0.05 USD / pm | E21: 0.05 USD / pm | F21: 0.05 USD / pm
A22: 24 | B22: Gemini AI key integration | C22: No | D22: Yes | E22: Yes | F22: Yes
A23: 26 | B23: External Calender sync | C23: No | D23: Yes | E23: Yes | F23: Yes
A24: 27 | B24: Coversion API integration | C24: Yes | D24: Yes | E24: Yes | F24: Yes
A25: 29 | B25: Email notification
A26: 30 | B26: -- Transactional | C26: Yes | D26: Yes | E26: Yes | F26: Yes
A27: 31 | B27: -- Marketing | C27: No | D27: Yes | E27: Yes | F27: Yes
A28: 33 | B28: Backlinks | C28: 3 | D28: 15 | E28: 100 | F28: Unlimited

Sheet Plan_Pricing_Proposed
A1: Base Pricing + Add-on Economics (Editable Proposal)
A3: Tier | B3: Monthly Base (USD) | C3: Annual Base (USD) | D3: Annual Discount % | E3: Status | F3: Notes | H3: Assumptions for missing base prices
A4: free | B4: 0 | C4: 0 | D4: =IF(B4=0,0,1-C4/(B4*12)) | E4: Confirmed | F4: From source file (monthly and annual = 0). | H4: Starter monthly (reference) | I4: =B5
A5: starter | B5: 6 | C5: 70 | D5: =IF(B5=0,0,1-C5/(B5*12)) | E5: Confirmed | F5: From source file (6 USD/month, 70 USD/year). | H5: Add-on pack monthly (instance+domain) | I5: 3
A6: freelance | B6: =ROUND($I$4 + MAX(0,$I$6-1)*$I$5*$I$8 + $I$10,0) | C6: =ROUND(B6*12*(1-$I$12),0) | D6: =IF(B6=0,0,1-C6/(B6*12)) | E6: Proposed | F6: Derived from included capacity + feature premium. Edit assumptions in H:I. | H6: Freelance included instances | I6: 10
A7: enterprise | B7: =ROUND($I$4 + MAX(0,$I$7-1)*$I$5*$I$9 + $I$11,0) | C7: =ROUND(B7*12*(1-$I$12),0) | D7: =IF(B7=0,0,1-C7/(B7*12)) | E7: Proposed | F7: Derived from volume discount and enterprise premium. Can switch to Custom pricing. | H7: Enterprise included instances | I7: 100
H8: Freelance volume factor | I8: 0.8
H9: Enterprise volume factor | I9: 0.4
A10: Add-ons & Overage | H10: Freelance feature premium | I10: 12
A11: Item | B11: Monthly Price (USD) | C11: Annual Price (USD) | D11: Unit | E11: Status | F11: Notes | H11: Enterprise feature premium | I11: 30
A12: Instance + Domain add-on pack | B12: 3 | C12: 24 | D12: per pack | E12: Confirmed | F12: From source row "Add-on Instance + Domain" | H12: Target annual discount (for proposed tiers) | I12: 0.15
A13: Additional inbox messages | B13: 0.05 | C13: =B13*12 | D13: per message | E13: Confirmed | F13: From source row "Additional messages"
A14: Custom domain fee on Free plan | B14: 10 | C14: =B14*12 | D14: per domain | E14: Inferred | F14: Source shows "10 USD" under Free for custom domains

Sheet Feature_Limits
A1: Normalized feature limits and capabilities per tier
A3: metric_key | B3: unit | C3: type | D3: free | E3: starter | F3: freelance | G3: enterprise | H3: overage_rate_usd_monthly | I3: source_note
A4: instances | B4: count | C4: limit | D4: 1 | E4: 1 | F4: 10 | G4: 100 | H4: 0 | I4: Source row "Instance"
A5: custom_domains_included | B5: count | C5: limit | D5: 0 | E5: 1 | F5: 10 | G5: 100 | H5: 0 | I5: Free tier shows 10 USD fee, so included set to 0 (inferred).
A6: pages_per_site | B6: count | C6: limit | D6: 5 | E6: 25 | F6: 25 | G6: 999999 | H6: 0 | I6: Source row "No of pages / per web"
A7: accessible_themes | B7: count | C7: limit | D7: 10 | E7: 100 | F7: 100 | G7: 100 | H7: 0 | I7: Source row "Accessible Themes"
A8: bookings_per_day | B8: count | C8: limit | D8: 10 | E8: 999999 | F8: 999999 | G8: 999999 | H8: 0 | I8: Source row "Bookings per day"
A9: active_services | B9: count | C9: limit | D9: 5 | E9: 999999 | F9: 999999 | G9: 999999 | H9: 0 | I9: Source row "Active Services to Display"
A10: inbox_messages_per_day | B10: count | C10: limit | D10: 50 | E10: 200 | F10: 200 | G10: 200 | H10: 0.05 | I10: Source row "Inbox Automation" + "Additional messages"
A11: backlinks | B11: count | C11: limit | D11: 3 | E11: 15 | F11: 100 | G11: 999999 | H11: 0 | I11: Source row "Backlinks"
A12: premium_templates | B12: flag(1/0) | C12: boolean | D12: 0 | E12: 1 | F12: 1 | G12: 1 | H12: 0 | I12: Source row "Premium Templates"
A13: staff_accounts | B13: flag(1/0) | C13: boolean | D13: 0 | E13: 1 | F13: 1 | G13: 1 | H13: 0 | I13: Source row "Staff accounts creation"
A14: seo_auto_generation | B14: flag(1/0) | C14: boolean | D14: 0 | E14: 1 | F14: 1 | G14: 1 | H14: 0 | I14: Source row "SEO Content Auto Generation"
A15: aeo_data_feeding | B15: flag(1/0) | C15: boolean | D15: 0 | E15: 1 | F15: 1 | G15: 1 | H15: 0 | I15: Source row "AEO Data feeding"
... A21: addon_instance_domain_available | B21: flag(1/0) | C21: boolean | D21: 0 | E21: 1 | F21: 1 | G21: 1 | H21: 3 | I21: Source row "Add-on Instance + Domain"

Sheet Usage_Input
A1: Usage Inputs (Edit blue cells)
A3: Current plan (free/starter/freelance/enterprise) | B3: starter
A4: Billing cycle (monthly/annual) | B4: monthly
A6: instances_needed | B6: 1
A7: custom_domains_needed | B7: 1
A8: pages_per_site_needed | B8: 25
A9: bookings_per_day_needed | B9: 40
A10: active_services_needed | B10: 10
A11: inbox_messages_per_day_needed | B11: 220
A12: backlinks_needed | B12: 20
A14: require_premium_templates (1/0) | B14: 1
A15: require_staff_accounts (1/0) | B15: 1
A16: require_marketing_email (1/0) | B16: 1
A17: require_seo_auto_generation (1/0) | B17: 1
A18: require_aeo_data_feeding (1/0) | B18: 1
... A20: require_external_calendar_sync (1/0) | B20: 1
A23: Tip: use 1 for required feature, 0 for not required.

Sheet Tier_Calculator
A1: Tier Fit + Total Cost Calculator
A3: tier | B3: fit_limits | C3: fit_required_features | D3: addon_packs | E3: overage_messages_per_day | F3: base_monthly | G3: overage_monthly | H3: total_monthly | I3: total_annual | J3: eligible_monthly_cost | K3: recommended
A4: free | B4: =AND(Usage_Input!$B$6<=INDEX(Feature_Limits!$D:$G,MATCH("instances",Feature_Limits!$A:$A,0),MATCH($A4,Feature_Limits!$D$3:$G$3,0)),Usage_Input!$B$7<=INDEX(Feature_Limits!$D:$G,MATCH("custom_domains_included",Feature_Limits!$A:$A,0),MATCH($A4,Feature_Limits!$D$3:$G$3,0)),Usage_Input!$B$8<=INDEX(Feature_Limits!$D:$G,MATCH("pages_per_site",Feature_Limits!$A:$A,0),MATCH($A4,Feature_Limits!$D$3:$G$3,0)),Usage_Input!$B$9<=INDEX(Feature_Limits!$D:$G,MATCH("bookings_per_day",Feature_Limits!$A:$A,0),MATCH($A4,Feature_Limits!$D$3:$G$3,0)),Usage_Input!$B$10<=INDEX(Feature_Limits!$D:$G,MATCH("active_services",Feature_Limits!$A:$A,0),MATCH($A4,Feature_Limits!$D$3:$G$3,0)),Usage_Input!$B$12<=INDEX(Feature_Limits!$D:$G,MATCH("backlinks",Feature_Limits!$A:$A,0),MATCH($A4,Feature_Limits!$D$3:$G$3,0))) | C4: =AND(Usage_Input!$B$14<=INDEX(Feature_Limits!$D:$G,MATCH("premium_templates",Feature_Limits!$A:$A,0),MATCH($A4,Feature_Limits!$D$3:$G$3,0)),Usage_Input!$B$15<=INDEX(Feature_Limits!$D:$G,MATCH("staff_accounts",Feature_Limits!$A:$A,0),MATCH($A4,Feature_Limits!$D$3:$G$3,0)),Usage_Input!$B$16<=INDEX(Feature_Limits!$D:$G,MATCH("marketing_email",Feature_Limits!$A:$A,0),MATCH($A4,Feature_Limits!$D$3:$G$3,0)),Usage_Input!$B$17<=INDEX(Feature_Limits!$D:$G,MATCH("seo_auto_generation",Feature_Limits!$A:$A,0),MATCH($A4,Feature_Limits!$D$3:$G$3,0)),Usage_Input!$B$18<=INDEX(Feature_Limits!$D:$G,MATCH("aeo_data_feeding",Feature_Limits!$A:$A,0),MATCH($A4,Feature_Limits!$D$3:$G$3,0)),Usage_Input!$B$19<=INDEX(Feature_Limits!$D:$G,MATCH("gemini_ai_key_integration",Feature_Limits!$A:$A,0),MATCH($A4,Feature_Limits!$D$3:$G$3,0)),Usage_Input!$B$20<=INDEX(Feature_Limits!$D:$G,MATCH("external_calendar_sync",Feature_Limits!$A:$A,0),MATCH($A4,Feature_Limits!$D$3:$G$3,0))) | D4: =IF(INDEX(Feature_Limits!$D:$G,MATCH("addon_instance_domain_available",Feature_Limits!$A:$A,0),MATCH($A4,Feature_Limits!$D$3:$G$3,0))=1,MAX(0,Usage_Input!$B$6-INDEX(Feature_Limits!$D:$G,MATCH("instances",Feature_Limits!$A:$A,0),MATCH($A4,Feature_Limits!$D$3:$G$3,0)),Usage_Input!$B$7-INDEX(Feature_Limits!$D:$G,MATCH("custom_domains_included",Feature_Limits!$A:$A,0),MATCH($A4,Feature_Limits!$D$3:$G$3,0))),0) | E4: =MAX(0,Usage_Input!$B$11-INDEX(Feature_Limits!$D:$G,MATCH("inbox_messages_per_day",Feature_Limits!$A:$A,0),MATCH($A4,Feature_Limits!$D$3:$G$3,0))) | F4: =INDEX(Plan_Pricing_Proposed!$B:$B,MATCH($A4,Plan_Pricing_Proposed!$A:$A,0)) | G4: =D4*INDEX(Feature_Limits!$H:$H,MATCH("addon_instance_domain_available",Feature_Limits!$A:$A,0))+E4*30*INDEX(Feature_Limits!$H:$H,MATCH("inbox_messages_per_day",Feature_Limits!$A:$A,0))+IF($A4="free",Usage_Input!$B$7*Plan_Pricing_Proposed!$B$14,0) | H4: =F4+G4 | I4: =INDEX(Plan_Pricing_Proposed!$C:$C,MATCH($A4,Plan_Pricing_Proposed!$A:$A,0))+D4*Plan_Pricing_Proposed!$C$12+E4*365*INDEX(Feature_Limits!$H:$H,MATCH("inbox_messages_per_day",Feature_Limits!$A:$A,0))+IF($A4="free",Usage_Input!$B$7*Plan_Pricing_Proposed!$C$14,0) | J4: =IF(AND(B4=TRUE,C4=TRUE),H4,999999999) | K4: =IF(AND(J4=MIN($J$4:$J$7),J4<999999999),"YES","")
A5: starter | B5: =AND(Usage_Input!$B$6<=INDEX(Feature_Limits!$D:$G,MATCH("instances",Feature_Limits!$A:$A,0),MATCH($A5,Feature_Limits!$D$3:$G$3,0)),Usage_Input!$B$7<=INDEX(Feature_Limits!$D:$G,MATCH("custom_domains_included",Feature_Limits!$A:$A,0),MATCH($A5,Feature_Limits!$D$3:$G$3,0)),Usage_Input!$B$8<=INDEX(Feature_Limits!$D:$G,MATCH("pages_per_site",Feature_Limits!$A:$A,0),MATCH($A5,Feature_Limits!$D$3:$G$3,0)),Usage_Input!$B$9<=INDEX(Feature_Limits!$D:$G,MATCH("bookings_per_day",Feature_Limits!$A:$A,0),MATCH($A5,Feature_Limits!$D$3:$G$3,0)),Usage_Input!$B$10<=INDEX(Feature_Limits!$D:$G,MATCH("active_services",Feature_Limits!$A:$A,0),MATCH($A5,Feature_Limits!$D$3:$G$3,0)),Usage_Input!$B$12<=INDEX(Feature_Limits!$D:$G,MATCH("backlinks",Feature_Limits!$A:$A,0),MATCH($A5,Feature_Limits!$D$3:$G$3,0))) | C5: =AND(Usage_Input!$B$14<=INDEX(Feature_Limits!$D:$G,MATCH("premium_templates",Feature_Limits!$A:$A,0),MATCH($A5,Feature_Limits!$D$3:$G$3,0)),Usage_Input!$B$15<=INDEX(Feature_Limits!$D:$G,MATCH("staff_accounts",Feature_Limits!$A:$A,0),MATCH($A5,Feature_Limits!$D$3:$G$3,0)),Usage_Input!$B$16<=INDEX(Feature_Limits!$D:$G,MATCH("marketing_email",Feature_Limits!$A:$A,0),MATCH($A5,Feature_Limits!$D$3:$G$3,0)),Usage_Input!$B$17<=INDEX(Feature_Limits!$D:$G,MATCH("seo_auto_generation",Feature_Limits!$A:$A,0),MATCH($A5,Feature_Limits!$D$3:$G$3,0)),Usage_Input!$B$18<=INDEX(Feature_Limits!$D:$G,MATCH("aeo_data_feeding",Feature_Limits!$A:$A,0),MATCH($A5,Feature_Limits!$D$3:$G$3,0)),Usage_Input!$B$19<=INDEX(Feature_Limits!$D:$G,MATCH("gemini_ai_key_integration",Feature_Limits!$A:$A,0),MATCH($A5,Feature_Limits!$D$3:$G$3,0)),Usage_Input!$B$20<=INDEX(Feature_Limits!$D:$G,MATCH("external_calendar_sync",Feature_Limits!$A:$A,0),MATCH($A5,Feature_Limits!$D$3:$G$3,0))) | D5: =IF(INDEX(Feature_Limits!$D:$G,MATCH("addon_instance_domain_available",Feature_Limits!$A:$A,0),MATCH($A5,Feature_Limits!$D$3:$G$3,0))=1,MAX(0,Usage_Input!$B$6-INDEX(Feature_Limits!$D:$G,MATCH("instances",Feature_Limits!$A:$A,0),MATCH($A5,Feature_Limits!$D$3:$G$3,0)),Usage_Input!$B$7-INDEX(Feature_Limits!$D:$G,MATCH("custom_domains_included",Feature_Limits!$A:$A,0),MATCH($A5,Feature_Limits!$D$3:$G$3,0))),0) | E5: =MAX(0,Usage_Input!$B$11-INDEX(Feature_Limits!$D:$G,MATCH("inbox_messages_per_day",Feature_Limits!$A:$A,0),MATCH($A5,Feature_Limits!$D$3:$G$3,0))) | F5: =INDEX(Plan_Pricing_Proposed!$B:$B,MATCH($A5,Plan_Pricing_Proposed!$A:$A,0)) | G5: =D5*INDEX(Feature_Limits!$H:$H,MATCH("addon_instance_domain_available",Feature_Limits!$A:$A,0))+E5*30*INDEX(Feature_Limits!$H:$H,MATCH("inbox_messages_per_day",Feature_Limits!$A:$A,0))+IF($A5="free",Usage_Input!$B$7*Plan_Pricing_Proposed!$B$14,0) | H5: =F5+G5 | I5: =INDEX(Plan_Pricing_Proposed!$C:$C,MATCH($A5,Plan_Pricing_Proposed!$A:$A,0))+D5*Plan_Pricing_Proposed!$C$12+E5*365*INDEX(Feature_Limits!$H:$H,MATCH("inbox_messages_per_day",Feature_Limits!$A:$A,0))+IF($A5="free",Usage_Input!$B$7*Plan_Pricing_Proposed!$C$14,0) | J5: =IF(AND(B5=TRUE,C5=TRUE),H5,999999999) | K5: =IF(AND(J5=MIN($J$4:$J$7),J5<999999999),"YES","")
A6: freelance | B6: =AND(Usage_Input!$B$6<=INDEX(Feature_Limits!$D:$G,MATCH("instances",Feature_Limits!$A:$A,0),MATCH($A6,Feature_Limits!$D$3:$G$3,0)),Usage_Input!$B$7<=INDEX(Feature_Limits!$D:$G,MATCH("custom_domains_included",Feature_Limits!$A:$A,0),MATCH($A6,Feature_Limits!$D$3:$G$3,0)),Usage_Input!$B$8<=INDEX(Feature_Limits!$D:$G,MATCH("pages_per_site",Feature_Limits!$A:$A,0),MATCH($A6,Feature_Limits!$D$3:$G$3,0)),Usage_Input!$B$9<=INDEX(Feature_Limits!$D:$G,MATCH("bookings_per_day",Feature_Limits!$A:$A,0),MATCH($A6,Feature_Limits!$D$3:$G$3,0)),Usage_Input!$B$10<=INDEX(Feature_Limits!$D:$G,MATCH("active_services",Feature_Limits!$A:$A,0),MATCH($A6,Feature_Limits!$D$3:$G$3,0)),Usage_Input!$B$12<=INDEX(Feature_Limits!$D:$G,MATCH("backlinks",Feature_Limits!$A:$A,0),MATCH($A6,Feature_Limits!$D$3:$G$3,0))) | C6: =AND(Usage_Input!$B$14<=INDEX(Feature_Limits!$D:$G,MATCH("premium_templates",Feature_Limits!$A:$A,0),MATCH($A6,Feature_Limits!$D$3:$G$3,0)),Usage_Input!$B$15<=INDEX(Feature_Limits!$D:$G,MATCH("staff_accounts",Feature_Limits!$A:$A,0),MATCH($A6,Feature_Limits!$D$3:$G$3,0)),Usage_Input!$B$16<=INDEX(Feature_Limits!$D:$G,MATCH("marketing_email",Feature_Limits!$A:$A,0),MATCH($A6,Feature_Limits!$D$3:$G$3,0)),Usage_Input!$B$17<=INDEX(Feature_Limits!$D:$G,MATCH("seo_auto_generation",Feature_Limits!$A:$A,0),MATCH($A6,Feature_Limits!$D$3:$G$3,0)),Usage_Input!$B$18<=INDEX(Feature_Limits!$D:$G,MATCH("aeo_data_feeding",Feature_Limits!$A:$A,0),MATCH($A6,Feature_Limits!$D$3:$G$3,0)),Usage_Input!$B$19<=INDEX(Feature_Limits!$D:$G,MATCH("gemini_ai_key_integration",Feature_Limits!$A:$A,0),MATCH($A6,Feature_Limits!$D$3:$G$3,0)),Usage_Input!$B$20<=INDEX(Feature_Limits!$D:$G,MATCH("external_calendar_sync",Feature_Limits!$A:$A,0),MATCH($A6,Feature_Limits!$D$3:$G$3,0))) | D6: =IF(INDEX(Feature_Limits!$D:$G,MATCH("addon_instance_domain_available",Feature_Limits!$A:$A,0),MATCH($A6,Feature_Limits!$D$3:$G$3,0))=1,MAX(0,Usage_Input!$B$6-INDEX(Feature_Limits!$D:$G,MATCH("instances",Feature_Limits!$A:$A,0),MATCH($A6,Feature_Limits!$D$3:$G$3,0)),Usage_Input!$B$7-INDEX(Feature_Limits!$D:$G,MATCH("custom_domains_included",Feature_Limits!$A:$A,0),MATCH($A6,Feature_Limits!$D$3:$G$3,0))),0) | E6: =MAX(0,Usage_Input!$B$11-INDEX(Feature_Limits!$D:$G,MATCH("inbox_messages_per_day",Feature_Limits!$A:$A,0),MATCH($A6,Feature_Limits!$D$3:$G$3,0))) | F6: =INDEX(Plan_Pricing_Proposed!$B:$B,MATCH($A6,Plan_Pricing_Proposed!$A:$A,0)) | G6: =D6*INDEX(Feature_Limits!$H:$H,MATCH("addon_instance_domain_available",Feature_Limits!$A:$A,0))+E6*30*INDEX(Feature_Limits!$H:$H,MATCH("inbox_messages_per_day",Feature_Limits!$A:$A,0))+IF($A6="free",Usage_Input!$B$7*Plan_Pricing_Proposed!$B$14,0) | H6: =F6+G6 | I6: =INDEX(Plan_Pricing_Proposed!$C:$C,MATCH($A6,Plan_Pricing_Proposed!$A:$A,0))+D6*Plan_Pricing_Proposed!$C$12+E6*365*INDEX(Feature_Limits!$H:$H,MATCH("inbox_messages_per_day",Feature_Limits!$A:$A,0))+IF($A6="free",Usage_Input!$B$7*Plan_Pricing_Proposed!$C$14,0) | J6: =IF(AND(B6=TRUE,C6=TRUE),H6,999999999) | K6: =IF(AND(J6=MIN($J$4:$J$7),J6<999999999),"YES","")
A7: enterprise | B7: =AND(Usage_Input!$B$6<=INDEX(Feature_Limits!$D:$G,MATCH("instances",Feature_Limits!$A:$A,0),MATCH($A7,Feature_Limits!$D$3:$G$3,0)),Usage_Input!$B$7<=INDEX(Feature_Limits!$D:$G,MATCH("custom_domains_included",Feature_Limits!$A:$A,0),MATCH($A7,Feature_Limits!$D$3:$G$3,0)),Usage_Input!$B$8<=INDEX(Feature_Limits!$D:$G,MATCH("pages_per_site",Feature_Limits!$A:$A,0),MATCH($A7,Feature_Limits!$D$3:$G$3,0)),Usage_Input!$B$9<=INDEX(Feature_Limits!$D:$G,MATCH("bookings_per_day",Feature_Limits!$A:$A,0),MATCH($A7,Feature_Limits!$D$3:$G$3,0)),Usage_Input!$B$10<=INDEX(Feature_Limits!$D:$G,MATCH("active_services",Feature_Limits!$A:$A,0),MATCH($A7,Feature_Limits!$D$3:$G$3,0)),Usage_Input!$B$12<=INDEX(Feature_Limits!$D:$G,MATCH("backlinks",Feature_Limits!$A:$A,0),MATCH($A7,Feature_Limits!$D$3:$G$3,0))) | C7: =AND(Usage_Input!$B$14<=INDEX(Feature_Limits!$D:$G,MATCH("premium_templates",Feature_Limits!$A:$A,0),MATCH($A7,Feature_Limits!$D$3:$G$3,0)),Usage_Input!$B$15<=INDEX(Feature_Limits!$D:$G,MATCH("staff_accounts",Feature_Limits!$A:$A,0),MATCH($A7,Feature_Limits!$D$3:$G$3,0)),Usage_Input!$B$16<=INDEX(Feature_Limits!$D:$G,MATCH("marketing_email",Feature_Limits!$A:$A,0),MATCH($A7,Feature_Limits!$D$3:$G$3,0)),Usage_Input!$B$17<=INDEX(Feature_Limits!$D:$G,MATCH("seo_auto_generation",Feature_Limits!$A:$A,0),MATCH($A7,Feature_Limits!$D$3:$G$3,0)),Usage_Input!$B$18<=INDEX(Feature_Limits!$D:$G,MATCH("aeo_data_feeding",Feature_Limits!$A:$A,0),MATCH($A7,Feature_Limits!$D$3:$G$3,0)),Usage_Input!$B$19<=INDEX(Feature_Limits!$D:$G,MATCH("gemini_ai_key_integration",Feature_Limits!$A:$A,0),MATCH($A7,Feature_Limits!$D$3:$G$3,0)),Usage_Input!$B$20<=INDEX(Feature_Limits!$D:$G,MATCH("external_calendar_sync",Feature_Limits!$A:$A,0),MATCH($A7,Feature_Limits!$D$3:$G$3,0))) | D7: =IF(INDEX(Feature_Limits!$D:$G,MATCH("addon_instance_domain_available",Feature_Limits!$A:$A,0),MATCH($A7,Feature_Limits!$D$3:$G$3,0))=1,MAX(0,Usage_Input!$B$6-INDEX(Feature_Limits!$D:$G,MATCH("instances",Feature_Limits!$A:$A,0),MATCH($A7,Feature_Limits!$D$3:$G$3,0)),Usage_Input!$B$7-INDEX(Feature_Limits!$D:$G,MATCH("custom_domains_included",Feature_Limits!$A:$A,0),MATCH($A7,Feature_Limits!$D$3:$G$3,0))),0) | E7: =MAX(0,Usage_Input!$B$11-INDEX(Feature_Limits!$D:$G,MATCH("inbox_messages_per_day",Feature_Limits!$A:$A,0),MATCH($A7,Feature_Limits!$D$3:$G$3,0))) | F7: =INDEX(Plan_Pricing_Proposed!$B:$B,MATCH($A7,Plan_Pricing_Proposed!$A:$A,0)) | G7: =D7*INDEX(Feature_Limits!$H:$H,MATCH("addon_instance_domain_available",Feature_Limits!$A:$A,0))+E7*30*INDEX(Feature_Limits!$H:$H,MATCH("inbox_messages_per_day",Feature_Limits!$A:$A,0))+IF($A7="free",Usage_Input!$B$7*Plan_Pricing_Proposed!$B$14,0) | H7: =F7+G7 | I7: =INDEX(Plan_Pricing_Proposed!$C:$C,MATCH($A7,Plan_Pricing_Proposed!$A:$A,0))+D7*Plan_Pricing_Proposed!$C$12+E7*365*INDEX(Feature_Limits!$H:$H,MATCH("inbox_messages_per_day",Feature_Limits!$A:$A,0))+IF($A7="free",Usage_Input!$B$7*Plan_Pricing_Proposed!$C$14,0) | J7: =IF(AND(B7=TRUE,C7=TRUE),H7,999999999) | K7: =IF(AND(J7=MIN($J$4:$J$7),J7<999999999),"YES","")
A10: Current plan monthly cost | B10: =INDEX(H4:H7,MATCH(Usage_Input!$B$3,A4:A7,0))
A11: Recommended tier | B11: =INDEX(A4:A7,MATCH("YES",K4:K7,0))
A12: Recommended monthly cost | B12: =MIN(J4:J7)
A13: Savings vs current plan | B13: =B10-B12

Sheet Upgrade_Mechanism
A1: Upgrade Passage Mechanism (How users move to higher tier)
A3: Live Recommendation
A4: Current plan | B4: =Usage_Input!B3
A5: Recommended next plan | B5: =Tier_Calculator!B11
A6: Upgrade needed? | B6: =IF(B4=B5,"No","Yes")
A7: Current monthly cost | B7: =Tier_Calculator!B10
A8: Recommended monthly cost | B8: =Tier_Calculator!B12
A9: Cost delta (current - recommended) | B9: =B7-B8
A12: Operational Rules
A13: Rule ID | B13: Trigger | C13: Condition | D13: Action | E13: Customer Message | F13: System Hook
A14: R1 | B14: Soft threshold | C14: Any key metric >= 80% of plan limit for 3 days | D14: Show in-app warning + email | E14: You are close to your plan limit. | F14: daily usage job + notification service
A15: R2 | B15: Hard threshold | C15: Any hard-limited metric > 100% | D15: Block new creation OR sell add-on pack | E15: Limit reached. Upgrade or buy add-on. | F15: write-time entitlement guard
A16: R3 | B16: Feature mismatch | C16: User enables a feature not in current plan | D16: Prompt immediate upgrade CTA | E16: This feature needs a higher plan. | F16: feature flag middleware
A17: R4 | B17: Economic trigger | C17: Overage spend > 80% of next-tier base for month | D17: Recommend plan switch | E17: Upgrade now to save costs. | F17: monthly billing optimizer
A18: R5 | B18: Stability trigger | C18: Trigger R4 for 2 consecutive months | D18: Auto-recommend in checkout flow | E18: Your usage trend fits the next tier. | F18: billing cycle finalizer
A19: R6 | B19: Downgrade protection | C19: Usage below 60% for 2 months | D19: Suggest downgrade before renewal | E19: You may reduce your plan cost. | F19: renewal pre-check job

Sheet Architecture_Blueprint
A1: Implementation Architecture (Mapped to current project)
A3: Current project alignment
A4: Area | B4: What exists | C4: Reference | D4: Action
A5: Existing tier enum | B5: free / starter / professional / enterprise | C5: packages/core/src/constants/index.ts | D5: Rename professional -> freelance OR map alias in pricing catalog
A6: Tenant plan field | B6: Tenant.plan (string, default starter) | C6: packages/database/prisma/schema.prisma | D6: Keep as source-of-truth for active plan key
A7: Feature toggles | B7: Per-instance feature toggle model already exists | C7: Feature toggles APIs | D7: Use toggles for runtime entitlement gates by plan
A9: Recommended pricing/billing data model (new tables)
A10: Table | B10: Purpose | C10: Key fields
A11: plan_catalog | B11: Versioned plan definitions | C11: plan_key, billing_cycle, base_price, currency, is_active, effective_from
A12: plan_entitlements | B12: Limits + booleans per plan | C12: plan_catalog_id, metric_key, limit_value, bool_value, overage_rate
A13: tenant_subscription | B13: Tenant billing state | C13: tenant_id, plan_key, status, cycle_start, cycle_end, next_plan_key
A14: usage_events | B14: Raw metered events | C14: tenant_id, metric_key, quantity, occurred_at, metadata_json
A15: usage_daily_rollup | B15: Fast aggregate for pricing | C15: tenant_id, metric_key, day, total_quantity
A16: invoice_line_items | B16: Charge components | C16: tenant_id, cycle, type(base/overage/addon), amount, details_json
A17: plan_change_log | B17: Audit trail for upgrades | C17: tenant_id, from_plan, to_plan, reason, actor, created_at
A20: Request and processing flow
A21: Step | B21: Service | C21: Input | D21: Output
A22: 1 | B22: API write path (booking/service/page/domain actions) | C22: Tenant action | D22: usage_events insert
A23: 2 | B23: Daily aggregator job | C23: usage_events | D23: usage_daily_rollup
A24: 3 | B24: Pricing engine job | C24: rollups + entitlements + base plan | D24: monthly projected charge + triggers
A25: 4 | B25: Entitlement middleware | C25: tenant.plan + plan_entitlements | D25: allow/deny + upgrade CTA
A26: 5 | B26: Billing finalizer | C26: cycle totals | D26: invoice_line_items + payment request
A27: 6 | B27: Plan switch handler | C27: user upgrade request or auto-recommend | D27: tenant_subscription update + plan_change_log
A30: Implementation rule: keep the pricing engine pure (input usage + plan config -> output invoice + recommendation), and keep API handlers thin.
